{"timestampedFiles":{"C:\\Users\\TIENDA\\Downloads\\api-rest-oracle\\src\\main\\java\\pe\\apirestoracle\\ApiRestOracleApplication.java":1606315157441,"C:\\Users\\TIENDA\\Downloads\\api-rest-oracle\\src\\main\\java\\pe\\apirestoracle\\controller\\HomeController.java":1606315157396,"C:\\Users\\TIENDA\\Downloads\\api-rest-oracle\\src\\main\\java\\pe\\apirestoracle\\controller\\ProductoController.java":1606426338095,"C:\\Users\\TIENDA\\Downloads\\api-rest-oracle\\src\\main\\java\\pe\\apirestoracle\\controller\\RolController.java":1606407551204,"C:\\Users\\TIENDA\\Downloads\\api-rest-oracle\\src\\main\\java\\pe\\apirestoracle\\daoImpl\\AccesoDaoImpl.java":1606315157379,"C:\\Users\\TIENDA\\Downloads\\api-rest-oracle\\src\\main\\java\\pe\\apirestoracle\\daoImpl\\ProductoDaoImp.java":1606425676435,"C:\\Users\\TIENDA\\Downloads\\api-rest-oracle\\src\\main\\java\\pe\\apirestoracle\\daoImpl\\RolDaoImpl.java":1606407345824,"C:\\Users\\TIENDA\\Downloads\\api-rest-oracle\\src\\main\\java\\pe\\apirestoracle\\daoImpl\\UsuarioDaoImpl.java":1606328686796,"C:\\Users\\TIENDA\\Downloads\\api-rest-oracle\\src\\main\\java\\pe\\apirestoracle\\dao\\AccesosDao.java":1606315157295,"C:\\Users\\TIENDA\\Downloads\\api-rest-oracle\\src\\main\\java\\pe\\apirestoracle\\dao\\ProductoDao.java":1606403763681,"C:\\Users\\TIENDA\\Downloads\\api-rest-oracle\\src\\main\\java\\pe\\apirestoracle\\dao\\RolDao.java":1606407011921,"C:\\Users\\TIENDA\\Downloads\\api-rest-oracle\\src\\main\\java\\pe\\apirestoracle\\dao\\UsuarioDao.java":1606315157398,"C:\\Users\\TIENDA\\Downloads\\api-rest-oracle\\src\\main\\java\\pe\\apirestoracle\\entity\\Acceso.java":1606315157312,"C:\\Users\\TIENDA\\Downloads\\api-rest-oracle\\src\\main\\java\\pe\\apirestoracle\\entity\\Producto.java":1606425606069,"C:\\Users\\TIENDA\\Downloads\\api-rest-oracle\\src\\main\\java\\pe\\apirestoracle\\entity\\Rol.java":1606315157375,"C:\\Users\\TIENDA\\Downloads\\api-rest-oracle\\src\\main\\java\\pe\\apirestoracle\\entity\\Usuario.java":1606315157388,"C:\\Users\\TIENDA\\Downloads\\api-rest-oracle\\src\\main\\java\\pe\\apirestoracle\\security\\AthorizationServiceConfig.java":1606422707660,"C:\\Users\\TIENDA\\Downloads\\api-rest-oracle\\src\\main\\java\\pe\\apirestoracle\\security\\InfoAdicionalToken.java":1606315157393,"C:\\Users\\TIENDA\\Downloads\\api-rest-oracle\\src\\main\\java\\pe\\apirestoracle\\security\\JwtConfig.java":1606315157307,"C:\\Users\\TIENDA\\Downloads\\api-rest-oracle\\src\\main\\java\\pe\\apirestoracle\\security\\ResourceServiceConfig.java":1606315157303,"C:\\Users\\TIENDA\\Downloads\\api-rest-oracle\\src\\main\\java\\pe\\apirestoracle\\security\\SpringSecurityConfig.java":1606315157282,"C:\\Users\\TIENDA\\Downloads\\api-rest-oracle\\src\\main\\java\\pe\\apirestoracle\\serviceImpl\\ProductoServiceImp.java":1606426282149,"C:\\Users\\TIENDA\\Downloads\\api-rest-oracle\\src\\main\\java\\pe\\apirestoracle\\serviceImpl\\RolServiceImpl.java":1606407527272,"C:\\Users\\TIENDA\\Downloads\\api-rest-oracle\\src\\main\\java\\pe\\apirestoracle\\serviceImpl\\UsuarioService.java":1606315157298,"C:\\Users\\TIENDA\\Downloads\\api-rest-oracle\\src\\main\\java\\pe\\apirestoracle\\service\\ProductoService.java":1606403378097,"C:\\Users\\TIENDA\\Downloads\\api-rest-oracle\\src\\main\\java\\pe\\apirestoracle\\service\\RolService.java":1606407518783},"symbols":[{"docURI":"file:///C:/Users/TIENDA/Downloads/api-rest-oracle/src/main/java/pe/apirestoracle/ApiRestOracleApplication.java","lastModified":1606315157441,"enhancedSymbol":{"symbol":{"name":"@+ \u0027apiRestOracleApplication\u0027 (@SpringBootApplication \u003c: @SpringBootConfiguration, @Configuration, @Component) ApiRestOracleApplication","kind":"Interface","location":{"uri":"file:///C:/Users/TIENDA/Downloads/api-rest-oracle/src/main/java/pe/apirestoracle/ApiRestOracleApplication.java","range":{"start":{"line":5,"character":0},"end":{"line":5,"character":22}}}},"additionalInformation":[{"type":"org.springframework.ide.vscode.boot.java.beans.BeansSymbolAddOnInformation","data":{"beanID":"apiRestOracleApplication"}}]}},{"docURI":"file:///C:/Users/TIENDA/Downloads/api-rest-oracle/src/main/java/pe/apirestoracle/controller/HomeController.java","lastModified":1606315157396,"enhancedSymbol":{"symbol":{"name":"@+ \u0027homeController\u0027 (@RestController \u003c: @Controller, @Component) HomeController","kind":"Interface","location":{"uri":"file:///C:/Users/TIENDA/Downloads/api-rest-oracle/src/main/java/pe/apirestoracle/controller/HomeController.java","range":{"start":{"line":5,"character":0},"end":{"line":5,"character":15}}}},"additionalInformation":[{"type":"org.springframework.ide.vscode.boot.java.beans.BeansSymbolAddOnInformation","data":{"beanID":"homeController"}}]}},{"docURI":"file:///C:/Users/TIENDA/Downloads/api-rest-oracle/src/main/java/pe/apirestoracle/controller/HomeController.java","lastModified":1606315157396,"enhancedSymbol":{"symbol":{"name":"@/","kind":"Interface","location":{"uri":"file:///C:/Users/TIENDA/Downloads/api-rest-oracle/src/main/java/pe/apirestoracle/controller/HomeController.java","range":{"start":{"line":7,"character":0},"end":{"line":7,"character":11}}}}}},{"docURI":"file:///C:/Users/TIENDA/Downloads/api-rest-oracle/src/main/java/pe/apirestoracle/controller/ProductoController.java","lastModified":1606426338095,"enhancedSymbol":{"symbol":{"name":"@+ \u0027productoController\u0027 (@RestController \u003c: @Controller, @Component) ProductoController","kind":"Interface","location":{"uri":"file:///C:/Users/TIENDA/Downloads/api-rest-oracle/src/main/java/pe/apirestoracle/controller/ProductoController.java","range":{"start":{"line":15,"character":0},"end":{"line":15,"character":15}}}},"additionalInformation":[{"type":"org.springframework.ide.vscode.boot.java.beans.BeansSymbolAddOnInformation","data":{"beanID":"productoController"}}]}},{"docURI":"file:///C:/Users/TIENDA/Downloads/api-rest-oracle/src/main/java/pe/apirestoracle/controller/ProductoController.java","lastModified":1606426338095,"enhancedSymbol":{"symbol":{"name":"@Autowired","kind":"Interface","location":{"uri":"file:///C:/Users/TIENDA/Downloads/api-rest-oracle/src/main/java/pe/apirestoracle/controller/ProductoController.java","range":{"start":{"line":18,"character":1},"end":{"line":18,"character":11}}}}}},{"docURI":"file:///C:/Users/TIENDA/Downloads/api-rest-oracle/src/main/java/pe/apirestoracle/controller/ProductoController.java","lastModified":1606426338095,"enhancedSymbol":{"symbol":{"name":"@CrossOrigin(origins\u003d\"http://localhost:4200\")","kind":"Interface","location":{"uri":"file:///C:/Users/TIENDA/Downloads/api-rest-oracle/src/main/java/pe/apirestoracle/controller/ProductoController.java","range":{"start":{"line":21,"character":1},"end":{"line":21,"character":48}}}}}},{"docURI":"file:///C:/Users/TIENDA/Downloads/api-rest-oracle/src/main/java/pe/apirestoracle/controller/ProductoController.java","lastModified":1606426338095,"enhancedSymbol":{"symbol":{"name":"@/producto/all -- GET","kind":"Interface","location":{"uri":"file:///C:/Users/TIENDA/Downloads/api-rest-oracle/src/main/java/pe/apirestoracle/controller/ProductoController.java","range":{"start":{"line":22,"character":1},"end":{"line":22,"character":20}}}}}},{"docURI":"file:///C:/Users/TIENDA/Downloads/api-rest-oracle/src/main/java/pe/apirestoracle/controller/ProductoController.java","lastModified":1606426338095,"enhancedSymbol":{"symbol":{"name":"@/producto/add -- POST","kind":"Interface","location":{"uri":"file:///C:/Users/TIENDA/Downloads/api-rest-oracle/src/main/java/pe/apirestoracle/controller/ProductoController.java","range":{"start":{"line":26,"character":1},"end":{"line":26,"character":21}}}}}},{"docURI":"file:///C:/Users/TIENDA/Downloads/api-rest-oracle/src/main/java/pe/apirestoracle/controller/ProductoController.java","lastModified":1606426338095,"enhancedSymbol":{"symbol":{"name":"@RequestBody","kind":"Interface","location":{"uri":"file:///C:/Users/TIENDA/Downloads/api-rest-oracle/src/main/java/pe/apirestoracle/controller/ProductoController.java","range":{"start":{"line":27,"character":19},"end":{"line":27,"character":31}}}}}},{"docURI":"file:///C:/Users/TIENDA/Downloads/api-rest-oracle/src/main/java/pe/apirestoracle/controller/RolController.java","lastModified":1606407551204,"enhancedSymbol":{"symbol":{"name":"@+ \u0027rolController\u0027 (@RestController \u003c: @Controller, @Component) RolController","kind":"Interface","location":{"uri":"file:///C:/Users/TIENDA/Downloads/api-rest-oracle/src/main/java/pe/apirestoracle/controller/RolController.java","range":{"start":{"line":19,"character":0},"end":{"line":19,"character":15}}}},"additionalInformation":[{"type":"org.springframework.ide.vscode.boot.java.beans.BeansSymbolAddOnInformation","data":{"beanID":"rolController"}}]}},{"docURI":"file:///C:/Users/TIENDA/Downloads/api-rest-oracle/src/main/java/pe/apirestoracle/controller/RolController.java","lastModified":1606407551204,"enhancedSymbol":{"symbol":{"name":"@CrossOrigin(origins\u003d\"*\",allowedHeaders\u003d\"*\")","kind":"Interface","location":{"uri":"file:///C:/Users/TIENDA/Downloads/api-rest-oracle/src/main/java/pe/apirestoracle/controller/RolController.java","range":{"start":{"line":20,"character":0},"end":{"line":20,"character":49}}}}}},{"docURI":"file:///C:/Users/TIENDA/Downloads/api-rest-oracle/src/main/java/pe/apirestoracle/controller/RolController.java","lastModified":1606407551204,"enhancedSymbol":{"symbol":{"name":"@Autowired","kind":"Interface","location":{"uri":"file:///C:/Users/TIENDA/Downloads/api-rest-oracle/src/main/java/pe/apirestoracle/controller/RolController.java","range":{"start":{"line":23,"character":0},"end":{"line":23,"character":10}}}}}},{"docURI":"file:///C:/Users/TIENDA/Downloads/api-rest-oracle/src/main/java/pe/apirestoracle/controller/RolController.java","lastModified":1606407551204,"enhancedSymbol":{"symbol":{"name":"@/roles/all -- GET","kind":"Interface","location":{"uri":"file:///C:/Users/TIENDA/Downloads/api-rest-oracle/src/main/java/pe/apirestoracle/controller/RolController.java","range":{"start":{"line":26,"character":0},"end":{"line":26,"character":19}}}}}},{"docURI":"file:///C:/Users/TIENDA/Downloads/api-rest-oracle/src/main/java/pe/apirestoracle/controller/RolController.java","lastModified":1606407551204,"enhancedSymbol":{"symbol":{"name":"@/roles/{id} -- GET","kind":"Interface","location":{"uri":"file:///C:/Users/TIENDA/Downloads/api-rest-oracle/src/main/java/pe/apirestoracle/controller/RolController.java","range":{"start":{"line":30,"character":0},"end":{"line":30,"character":20}}}}}},{"docURI":"file:///C:/Users/TIENDA/Downloads/api-rest-oracle/src/main/java/pe/apirestoracle/controller/RolController.java","lastModified":1606407551204,"enhancedSymbol":{"symbol":{"name":"@PathVariable","kind":"Interface","location":{"uri":"file:///C:/Users/TIENDA/Downloads/api-rest-oracle/src/main/java/pe/apirestoracle/controller/RolController.java","range":{"start":{"line":31,"character":38},"end":{"line":31,"character":51}}}}}},{"docURI":"file:///C:/Users/TIENDA/Downloads/api-rest-oracle/src/main/java/pe/apirestoracle/controller/RolController.java","lastModified":1606407551204,"enhancedSymbol":{"symbol":{"name":"@/roles/delete/{id} -- DELETE","kind":"Interface","location":{"uri":"file:///C:/Users/TIENDA/Downloads/api-rest-oracle/src/main/java/pe/apirestoracle/controller/RolController.java","range":{"start":{"line":40,"character":0},"end":{"line":40,"character":30}}}}}},{"docURI":"file:///C:/Users/TIENDA/Downloads/api-rest-oracle/src/main/java/pe/apirestoracle/controller/RolController.java","lastModified":1606407551204,"enhancedSymbol":{"symbol":{"name":"@PathVariable","kind":"Interface","location":{"uri":"file:///C:/Users/TIENDA/Downloads/api-rest-oracle/src/main/java/pe/apirestoracle/controller/RolController.java","range":{"start":{"line":41,"character":18},"end":{"line":41,"character":31}}}}}},{"docURI":"file:///C:/Users/TIENDA/Downloads/api-rest-oracle/src/main/java/pe/apirestoracle/controller/RolController.java","lastModified":1606407551204,"enhancedSymbol":{"symbol":{"name":"@/roles/add -- POST","kind":"Interface","location":{"uri":"file:///C:/Users/TIENDA/Downloads/api-rest-oracle/src/main/java/pe/apirestoracle/controller/RolController.java","range":{"start":{"line":45,"character":0},"end":{"line":45,"character":20}}}}}},{"docURI":"file:///C:/Users/TIENDA/Downloads/api-rest-oracle/src/main/java/pe/apirestoracle/controller/RolController.java","lastModified":1606407551204,"enhancedSymbol":{"symbol":{"name":"@RequestBody","kind":"Interface","location":{"uri":"file:///C:/Users/TIENDA/Downloads/api-rest-oracle/src/main/java/pe/apirestoracle/controller/RolController.java","range":{"start":{"line":46,"character":18},"end":{"line":46,"character":30}}}}}},{"docURI":"file:///C:/Users/TIENDA/Downloads/api-rest-oracle/src/main/java/pe/apirestoracle/controller/RolController.java","lastModified":1606407551204,"enhancedSymbol":{"symbol":{"name":"@/roles/update/{id} -- PUT","kind":"Interface","location":{"uri":"file:///C:/Users/TIENDA/Downloads/api-rest-oracle/src/main/java/pe/apirestoracle/controller/RolController.java","range":{"start":{"line":51,"character":0},"end":{"line":51,"character":27}}}}}},{"docURI":"file:///C:/Users/TIENDA/Downloads/api-rest-oracle/src/main/java/pe/apirestoracle/controller/RolController.java","lastModified":1606407551204,"enhancedSymbol":{"symbol":{"name":"@RequestBody","kind":"Interface","location":{"uri":"file:///C:/Users/TIENDA/Downloads/api-rest-oracle/src/main/java/pe/apirestoracle/controller/RolController.java","range":{"start":{"line":52,"character":16},"end":{"line":52,"character":28}}}}}},{"docURI":"file:///C:/Users/TIENDA/Downloads/api-rest-oracle/src/main/java/pe/apirestoracle/controller/RolController.java","lastModified":1606407551204,"enhancedSymbol":{"symbol":{"name":"@PathVariable","kind":"Interface","location":{"uri":"file:///C:/Users/TIENDA/Downloads/api-rest-oracle/src/main/java/pe/apirestoracle/controller/RolController.java","range":{"start":{"line":52,"character":36},"end":{"line":52,"character":49}}}}}},{"docURI":"file:///C:/Users/TIENDA/Downloads/api-rest-oracle/src/main/java/pe/apirestoracle/controller/RolController.java","lastModified":1606407551204,"enhancedSymbol":{"symbol":{"name":"@/roles/update/logica/{id} -- PUT","kind":"Interface","location":{"uri":"file:///C:/Users/TIENDA/Downloads/api-rest-oracle/src/main/java/pe/apirestoracle/controller/RolController.java","range":{"start":{"line":60,"character":0},"end":{"line":60,"character":34}}}}}},{"docURI":"file:///C:/Users/TIENDA/Downloads/api-rest-oracle/src/main/java/pe/apirestoracle/controller/RolController.java","lastModified":1606407551204,"enhancedSymbol":{"symbol":{"name":"@PathVariable","kind":"Interface","location":{"uri":"file:///C:/Users/TIENDA/Downloads/api-rest-oracle/src/main/java/pe/apirestoracle/controller/RolController.java","range":{"start":{"line":61,"character":16},"end":{"line":61,"character":29}}}}}},{"docURI":"file:///C:/Users/TIENDA/Downloads/api-rest-oracle/src/main/java/pe/apirestoracle/daoImpl/AccesoDaoImpl.java","lastModified":1606315157379,"enhancedSymbol":{"symbol":{"name":"@Autowired","kind":"Interface","location":{"uri":"file:///C:/Users/TIENDA/Downloads/api-rest-oracle/src/main/java/pe/apirestoracle/daoImpl/AccesoDaoImpl.java","range":{"start":{"line":14,"character":1},"end":{"line":14,"character":11}}}}}},{"docURI":"file:///C:/Users/TIENDA/Downloads/api-rest-oracle/src/main/java/pe/apirestoracle/daoImpl/ProductoDaoImp.java","lastModified":1606425676435,"enhancedSymbol":{"symbol":{"name":"@+ \u0027productoDaoImp\u0027 (@Component) ProductoDaoImp","kind":"Interface","location":{"uri":"file:///C:/Users/TIENDA/Downloads/api-rest-oracle/src/main/java/pe/apirestoracle/daoImpl/ProductoDaoImp.java","range":{"start":{"line":15,"character":0},"end":{"line":15,"character":10}}}},"additionalInformation":[{"type":"org.springframework.ide.vscode.boot.java.beans.BeansSymbolAddOnInformation","data":{"beanID":"productoDaoImp"}}]}},{"docURI":"file:///C:/Users/TIENDA/Downloads/api-rest-oracle/src/main/java/pe/apirestoracle/daoImpl/ProductoDaoImp.java","lastModified":1606425676435,"enhancedSymbol":{"symbol":{"name":"@Autowired","kind":"Interface","location":{"uri":"file:///C:/Users/TIENDA/Downloads/api-rest-oracle/src/main/java/pe/apirestoracle/daoImpl/ProductoDaoImp.java","range":{"start":{"line":17,"character":0},"end":{"line":17,"character":10}}}}}},{"docURI":"file:///C:/Users/TIENDA/Downloads/api-rest-oracle/src/main/java/pe/apirestoracle/daoImpl/RolDaoImpl.java","lastModified":1606407345824,"enhancedSymbol":{"symbol":{"name":"@+ \u0027rolDaoImpl\u0027 (@Component) RolDaoImpl","kind":"Interface","location":{"uri":"file:///C:/Users/TIENDA/Downloads/api-rest-oracle/src/main/java/pe/apirestoracle/daoImpl/RolDaoImpl.java","range":{"start":{"line":27,"character":0},"end":{"line":27,"character":10}}}},"additionalInformation":[{"type":"org.springframework.ide.vscode.boot.java.beans.BeansSymbolAddOnInformation","data":{"beanID":"rolDaoImpl"}}]}},{"docURI":"file:///C:/Users/TIENDA/Downloads/api-rest-oracle/src/main/java/pe/apirestoracle/daoImpl/RolDaoImpl.java","lastModified":1606407345824,"enhancedSymbol":{"symbol":{"name":"@Autowired","kind":"Interface","location":{"uri":"file:///C:/Users/TIENDA/Downloads/api-rest-oracle/src/main/java/pe/apirestoracle/daoImpl/RolDaoImpl.java","range":{"start":{"line":29,"character":0},"end":{"line":29,"character":10}}}}}},{"docURI":"file:///C:/Users/TIENDA/Downloads/api-rest-oracle/src/main/java/pe/apirestoracle/daoImpl/UsuarioDaoImpl.java","lastModified":1606328686796,"enhancedSymbol":{"symbol":{"name":"@Autowired","kind":"Interface","location":{"uri":"file:///C:/Users/TIENDA/Downloads/api-rest-oracle/src/main/java/pe/apirestoracle/daoImpl/UsuarioDaoImpl.java","range":{"start":{"line":16,"character":0},"end":{"line":16,"character":10}}}}}},{"docURI":"file:///C:/Users/TIENDA/Downloads/api-rest-oracle/src/main/java/pe/apirestoracle/security/AthorizationServiceConfig.java","lastModified":1606422707660,"enhancedSymbol":{"symbol":{"name":"@+ \u0027athorizationServiceConfig\u0027 (@Configuration \u003c: @Component) AthorizationServiceConfig","kind":"Interface","location":{"uri":"file:///C:/Users/TIENDA/Downloads/api-rest-oracle/src/main/java/pe/apirestoracle/security/AthorizationServiceConfig.java","range":{"start":{"line":17,"character":0},"end":{"line":17,"character":14}}}},"additionalInformation":[{"type":"org.springframework.ide.vscode.boot.java.beans.BeansSymbolAddOnInformation","data":{"beanID":"athorizationServiceConfig"}}]}},{"docURI":"file:///C:/Users/TIENDA/Downloads/api-rest-oracle/src/main/java/pe/apirestoracle/security/AthorizationServiceConfig.java","lastModified":1606422707660,"enhancedSymbol":{"symbol":{"name":"@EnableAuthorizationServer","kind":"Interface","location":{"uri":"file:///C:/Users/TIENDA/Downloads/api-rest-oracle/src/main/java/pe/apirestoracle/security/AthorizationServiceConfig.java","range":{"start":{"line":18,"character":0},"end":{"line":18,"character":26}}}}}},{"docURI":"file:///C:/Users/TIENDA/Downloads/api-rest-oracle/src/main/java/pe/apirestoracle/security/AthorizationServiceConfig.java","lastModified":1606422707660,"enhancedSymbol":{"symbol":{"name":"@Autowired","kind":"Interface","location":{"uri":"file:///C:/Users/TIENDA/Downloads/api-rest-oracle/src/main/java/pe/apirestoracle/security/AthorizationServiceConfig.java","range":{"start":{"line":20,"character":1},"end":{"line":20,"character":11}}}}}},{"docURI":"file:///C:/Users/TIENDA/Downloads/api-rest-oracle/src/main/java/pe/apirestoracle/security/AthorizationServiceConfig.java","lastModified":1606422707660,"enhancedSymbol":{"symbol":{"name":"@Autowired","kind":"Interface","location":{"uri":"file:///C:/Users/TIENDA/Downloads/api-rest-oracle/src/main/java/pe/apirestoracle/security/AthorizationServiceConfig.java","range":{"start":{"line":22,"character":1},"end":{"line":22,"character":11}}}}}},{"docURI":"file:///C:/Users/TIENDA/Downloads/api-rest-oracle/src/main/java/pe/apirestoracle/security/AthorizationServiceConfig.java","lastModified":1606422707660,"enhancedSymbol":{"symbol":{"name":"@Autowired","kind":"Interface","location":{"uri":"file:///C:/Users/TIENDA/Downloads/api-rest-oracle/src/main/java/pe/apirestoracle/security/AthorizationServiceConfig.java","range":{"start":{"line":24,"character":1},"end":{"line":24,"character":11}}}}}},{"docURI":"file:///C:/Users/TIENDA/Downloads/api-rest-oracle/src/main/java/pe/apirestoracle/security/AthorizationServiceConfig.java","lastModified":1606422707660,"enhancedSymbol":{"symbol":{"name":"@+ \u0027tokenStore\u0027 (@Bean) JwtTokenStore","kind":"Interface","location":{"uri":"file:///C:/Users/TIENDA/Downloads/api-rest-oracle/src/main/java/pe/apirestoracle/security/AthorizationServiceConfig.java","range":{"start":{"line":51,"character":1},"end":{"line":51,"character":6}}}},"additionalInformation":[{"type":"org.springframework.ide.vscode.boot.java.beans.BeansSymbolAddOnInformation","data":{"beanID":"tokenStore"}}]}},{"docURI":"file:///C:/Users/TIENDA/Downloads/api-rest-oracle/src/main/java/pe/apirestoracle/security/AthorizationServiceConfig.java","lastModified":1606422707660,"enhancedSymbol":{"symbol":{"name":"@+ \u0027accessTokenConverter\u0027 (@Bean) JwtAccessTokenConverter","kind":"Interface","location":{"uri":"file:///C:/Users/TIENDA/Downloads/api-rest-oracle/src/main/java/pe/apirestoracle/security/AthorizationServiceConfig.java","range":{"start":{"line":56,"character":1},"end":{"line":56,"character":6}}}},"additionalInformation":[{"type":"org.springframework.ide.vscode.boot.java.beans.BeansSymbolAddOnInformation","data":{"beanID":"accessTokenConverter"}}]}},{"docURI":"file:///C:/Users/TIENDA/Downloads/api-rest-oracle/src/main/java/pe/apirestoracle/security/InfoAdicionalToken.java","lastModified":1606315157393,"enhancedSymbol":{"symbol":{"name":"@+ \u0027infoAdicionalToken\u0027 (@Component) InfoAdicionalToken","kind":"Interface","location":{"uri":"file:///C:/Users/TIENDA/Downloads/api-rest-oracle/src/main/java/pe/apirestoracle/security/InfoAdicionalToken.java","range":{"start":{"line":14,"character":0},"end":{"line":14,"character":10}}}},"additionalInformation":[{"type":"org.springframework.ide.vscode.boot.java.beans.BeansSymbolAddOnInformation","data":{"beanID":"infoAdicionalToken"}}]}},{"docURI":"file:///C:/Users/TIENDA/Downloads/api-rest-oracle/src/main/java/pe/apirestoracle/security/InfoAdicionalToken.java","lastModified":1606315157393,"enhancedSymbol":{"symbol":{"name":"@Autowired","kind":"Interface","location":{"uri":"file:///C:/Users/TIENDA/Downloads/api-rest-oracle/src/main/java/pe/apirestoracle/security/InfoAdicionalToken.java","range":{"start":{"line":16,"character":1},"end":{"line":16,"character":11}}}}}},{"docURI":"file:///C:/Users/TIENDA/Downloads/api-rest-oracle/src/main/java/pe/apirestoracle/security/ResourceServiceConfig.java","lastModified":1606315157303,"enhancedSymbol":{"symbol":{"name":"@+ \u0027resourceServiceConfig\u0027 (@Configuration \u003c: @Component) ResourceServiceConfig","kind":"Interface","location":{"uri":"file:///C:/Users/TIENDA/Downloads/api-rest-oracle/src/main/java/pe/apirestoracle/security/ResourceServiceConfig.java","range":{"start":{"line":17,"character":0},"end":{"line":17,"character":14}}}},"additionalInformation":[{"type":"org.springframework.ide.vscode.boot.java.beans.BeansSymbolAddOnInformation","data":{"beanID":"resourceServiceConfig"}}]}},{"docURI":"file:///C:/Users/TIENDA/Downloads/api-rest-oracle/src/main/java/pe/apirestoracle/security/ResourceServiceConfig.java","lastModified":1606315157303,"enhancedSymbol":{"symbol":{"name":"@EnableResourceServer","kind":"Interface","location":{"uri":"file:///C:/Users/TIENDA/Downloads/api-rest-oracle/src/main/java/pe/apirestoracle/security/ResourceServiceConfig.java","range":{"start":{"line":18,"character":0},"end":{"line":18,"character":21}}}}}},{"docURI":"file:///C:/Users/TIENDA/Downloads/api-rest-oracle/src/main/java/pe/apirestoracle/security/ResourceServiceConfig.java","lastModified":1606315157303,"enhancedSymbol":{"symbol":{"name":"@+ \u0027corsConfigurationSource\u0027 (@Bean) CorsConfigurationSource","kind":"Interface","location":{"uri":"file:///C:/Users/TIENDA/Downloads/api-rest-oracle/src/main/java/pe/apirestoracle/security/ResourceServiceConfig.java","range":{"start":{"line":28,"character":1},"end":{"line":28,"character":6}}}},"additionalInformation":[{"type":"org.springframework.ide.vscode.boot.java.beans.BeansSymbolAddOnInformation","data":{"beanID":"corsConfigurationSource"}}]}},{"docURI":"file:///C:/Users/TIENDA/Downloads/api-rest-oracle/src/main/java/pe/apirestoracle/security/ResourceServiceConfig.java","lastModified":1606315157303,"enhancedSymbol":{"symbol":{"name":"@+ \u0027corsFilter\u0027 (@Bean) FilterRegistrationBean\u003cCorsFilter\u003e","kind":"Interface","location":{"uri":"file:///C:/Users/TIENDA/Downloads/api-rest-oracle/src/main/java/pe/apirestoracle/security/ResourceServiceConfig.java","range":{"start":{"line":39,"character":1},"end":{"line":39,"character":6}}}},"additionalInformation":[{"type":"org.springframework.ide.vscode.boot.java.beans.BeansSymbolAddOnInformation","data":{"beanID":"corsFilter"}}]}},{"docURI":"file:///C:/Users/TIENDA/Downloads/api-rest-oracle/src/main/java/pe/apirestoracle/security/SpringSecurityConfig.java","lastModified":1606315157282,"enhancedSymbol":{"symbol":{"name":"@+ \u0027springSecurityConfig\u0027 (@EnableGlobalMethodSecurity \u003c: @EnableGlobalAuthentication, @Configuration, @Component) SpringSecurityConfig","kind":"Interface","location":{"uri":"file:///C:/Users/TIENDA/Downloads/api-rest-oracle/src/main/java/pe/apirestoracle/security/SpringSecurityConfig.java","range":{"start":{"line":15,"character":0},"end":{"line":15,"character":50}}}},"additionalInformation":[{"type":"org.springframework.ide.vscode.boot.java.beans.BeansSymbolAddOnInformation","data":{"beanID":"springSecurityConfig"}}]}},{"docURI":"file:///C:/Users/TIENDA/Downloads/api-rest-oracle/src/main/java/pe/apirestoracle/security/SpringSecurityConfig.java","lastModified":1606315157282,"enhancedSymbol":{"symbol":{"name":"@+ \u0027springSecurityConfig\u0027 (@Configuration \u003c: @Component) SpringSecurityConfig","kind":"Interface","location":{"uri":"file:///C:/Users/TIENDA/Downloads/api-rest-oracle/src/main/java/pe/apirestoracle/security/SpringSecurityConfig.java","range":{"start":{"line":16,"character":0},"end":{"line":16,"character":14}}}},"additionalInformation":[{"type":"org.springframework.ide.vscode.boot.java.beans.BeansSymbolAddOnInformation","data":{"beanID":"springSecurityConfig"}}]}},{"docURI":"file:///C:/Users/TIENDA/Downloads/api-rest-oracle/src/main/java/pe/apirestoracle/security/SpringSecurityConfig.java","lastModified":1606315157282,"enhancedSymbol":{"symbol":{"name":"@Autowired","kind":"Interface","location":{"uri":"file:///C:/Users/TIENDA/Downloads/api-rest-oracle/src/main/java/pe/apirestoracle/security/SpringSecurityConfig.java","range":{"start":{"line":18,"character":1},"end":{"line":18,"character":11}}}}}},{"docURI":"file:///C:/Users/TIENDA/Downloads/api-rest-oracle/src/main/java/pe/apirestoracle/security/SpringSecurityConfig.java","lastModified":1606315157282,"enhancedSymbol":{"symbol":{"name":"@+ \u0027passwordEncoder\u0027 (@Bean) BCryptPasswordEncoder","kind":"Interface","location":{"uri":"file:///C:/Users/TIENDA/Downloads/api-rest-oracle/src/main/java/pe/apirestoracle/security/SpringSecurityConfig.java","range":{"start":{"line":21,"character":1},"end":{"line":21,"character":6}}}},"additionalInformation":[{"type":"org.springframework.ide.vscode.boot.java.beans.BeansSymbolAddOnInformation","data":{"beanID":"passwordEncoder"}}]}},{"docURI":"file:///C:/Users/TIENDA/Downloads/api-rest-oracle/src/main/java/pe/apirestoracle/security/SpringSecurityConfig.java","lastModified":1606315157282,"enhancedSymbol":{"symbol":{"name":"@+ \u0027authenticationManager\u0027 (@Bean @Override) AuthenticationManager","kind":"Interface","location":{"uri":"file:///C:/Users/TIENDA/Downloads/api-rest-oracle/src/main/java/pe/apirestoracle/security/SpringSecurityConfig.java","range":{"start":{"line":31,"character":1},"end":{"line":31,"character":6}}}},"additionalInformation":[{"type":"org.springframework.ide.vscode.boot.java.beans.BeansSymbolAddOnInformation","data":{"beanID":"authenticationManager"}}]}},{"docURI":"file:///C:/Users/TIENDA/Downloads/api-rest-oracle/src/main/java/pe/apirestoracle/serviceImpl/ProductoServiceImp.java","lastModified":1606426282149,"enhancedSymbol":{"symbol":{"name":"@+ \u0027productoServiceImp\u0027 (@Service \u003c: @Component) ProductoServiceImp","kind":"Interface","location":{"uri":"file:///C:/Users/TIENDA/Downloads/api-rest-oracle/src/main/java/pe/apirestoracle/serviceImpl/ProductoServiceImp.java","range":{"start":{"line":11,"character":0},"end":{"line":11,"character":8}}}},"additionalInformation":[{"type":"org.springframework.ide.vscode.boot.java.beans.BeansSymbolAddOnInformation","data":{"beanID":"productoServiceImp"}}]}},{"docURI":"file:///C:/Users/TIENDA/Downloads/api-rest-oracle/src/main/java/pe/apirestoracle/serviceImpl/ProductoServiceImp.java","lastModified":1606426282149,"enhancedSymbol":{"symbol":{"name":"@Autowired","kind":"Interface","location":{"uri":"file:///C:/Users/TIENDA/Downloads/api-rest-oracle/src/main/java/pe/apirestoracle/serviceImpl/ProductoServiceImp.java","range":{"start":{"line":13,"character":1},"end":{"line":13,"character":11}}}}}},{"docURI":"file:///C:/Users/TIENDA/Downloads/api-rest-oracle/src/main/java/pe/apirestoracle/serviceImpl/RolServiceImpl.java","lastModified":1606407527272,"enhancedSymbol":{"symbol":{"name":"@+ \u0027rolServiceImpl\u0027 (@Service \u003c: @Component) RolServiceImpl","kind":"Interface","location":{"uri":"file:///C:/Users/TIENDA/Downloads/api-rest-oracle/src/main/java/pe/apirestoracle/serviceImpl/RolServiceImpl.java","range":{"start":{"line":11,"character":0},"end":{"line":11,"character":8}}}},"additionalInformation":[{"type":"org.springframework.ide.vscode.boot.java.beans.BeansSymbolAddOnInformation","data":{"beanID":"rolServiceImpl"}}]}},{"docURI":"file:///C:/Users/TIENDA/Downloads/api-rest-oracle/src/main/java/pe/apirestoracle/serviceImpl/RolServiceImpl.java","lastModified":1606407527272,"enhancedSymbol":{"symbol":{"name":"@Autowired","kind":"Interface","location":{"uri":"file:///C:/Users/TIENDA/Downloads/api-rest-oracle/src/main/java/pe/apirestoracle/serviceImpl/RolServiceImpl.java","range":{"start":{"line":13,"character":0},"end":{"line":13,"character":10}}}}}},{"docURI":"file:///C:/Users/TIENDA/Downloads/api-rest-oracle/src/main/java/pe/apirestoracle/serviceImpl/UsuarioService.java","lastModified":1606315157298,"enhancedSymbol":{"symbol":{"name":"@+ \u0027usuarioService\u0027 (@Service \u003c: @Component) UsuarioService","kind":"Interface","location":{"uri":"file:///C:/Users/TIENDA/Downloads/api-rest-oracle/src/main/java/pe/apirestoracle/serviceImpl/UsuarioService.java","range":{"start":{"line":21,"character":0},"end":{"line":21,"character":23}}}},"additionalInformation":[{"type":"org.springframework.ide.vscode.boot.java.beans.BeansSymbolAddOnInformation","data":{"beanID":"usuarioService"}}]}},{"docURI":"file:///C:/Users/TIENDA/Downloads/api-rest-oracle/src/main/java/pe/apirestoracle/serviceImpl/UsuarioService.java","lastModified":1606315157298,"enhancedSymbol":{"symbol":{"name":"@Autowired","kind":"Interface","location":{"uri":"file:///C:/Users/TIENDA/Downloads/api-rest-oracle/src/main/java/pe/apirestoracle/serviceImpl/UsuarioService.java","range":{"start":{"line":24,"character":3},"end":{"line":24,"character":13}}}}}},{"docURI":"file:///C:/Users/TIENDA/Downloads/api-rest-oracle/src/main/java/pe/apirestoracle/serviceImpl/UsuarioService.java","lastModified":1606315157298,"enhancedSymbol":{"symbol":{"name":"@Autowired","kind":"Interface","location":{"uri":"file:///C:/Users/TIENDA/Downloads/api-rest-oracle/src/main/java/pe/apirestoracle/serviceImpl/UsuarioService.java","range":{"start":{"line":26,"character":3},"end":{"line":26,"character":13}}}}}},{"docURI":"file:///C:/Users/TIENDA/Downloads/api-rest-oracle/src/main/java/pe/apirestoracle/serviceImpl/UsuarioService.java","lastModified":1606315157298,"enhancedSymbol":{"symbol":{"name":"@Transactional(readOnly\u003dtrue)","kind":"Interface","location":{"uri":"file:///C:/Users/TIENDA/Downloads/api-rest-oracle/src/main/java/pe/apirestoracle/serviceImpl/UsuarioService.java","range":{"start":{"line":30,"character":1},"end":{"line":30,"character":32}}}}}}],"dependencies":{}}